Metadata-Version: 1.1
Name: urllib-gssapi
Version: 1.0.2
Summary: GSSAPI over HTTP Negotiate/SPNEGO support for urllib/urllib2
Home-page: http://github.com/pythongssapi/urllib-gssapi/
Author: Tim Olsen, Will Thames, and The Python GSSAPI Team
Author-email: rharwood@redhat.com
License: Apache 2.0
Keywords: urllib2 kerberos http https negotiate spnego gssapi
Platform: UNKNOWN
Classifier: Intended Audience :: Developers
Classifier: License :: OSI Approved :: Apache Software License
Classifier: Natural Language :: English
Classifier: Operating System :: POSIX :: Linux
Classifier: Programming Language :: Python
Classifier: Topic :: Internet :: WWW/HTTP
Classifier: Topic :: Software Development :: Libraries
Classifier: Topic :: Software Development :: Libraries :: Python Modules
Classifier: Topic :: System :: Systems Administration :: Authentication/Directory
